Workbook

Sheet Esto
A1: Código | B1: Nome do Perfume | C1: Categoria | D1: Inicio | E1: Vendido | F1: Total | G1: Coluna1
A2: B00001 | B2: Brz Blossom | C2: BODYSPLASH | D2: 11 | E2: =SUMIF(Vm!$C:$C,$A2,Vm!$F:$F) -> 2 | F2: =SUM(D2-E2) -> 9 | G2: OK | I2: total | J2: Inicio | K2: Vendida | L2: Atual
A3: B00002 | B3: Nectar Crystal | C3: BODYSPLASH | D3: 16 | E3: =SUMIF(Vm!$C:$C,$A3,Vm!$F:$F) -> 3 | F3: =SUM(D3-E3) -> 13 | G3: OK | I3: bodysplah | J3: =SUM(#REF!) -> #REF! | K3: =SUM(E2:E6) -> 14 | L3: =SUM(F2:F6) -> 51
A4: B00003 | B4: Rubi | C4: BODYSPLASH | D4: 15 | E4: =SUMIF(Vm!$C:$C,$A4,Vm!$F:$F) -> 1 | F4: =SUM(D4-E4) -> 14 | G4: OK | I4: 10ml | J4: =SUM(#REF!) -> #REF! | K4: =SUM(E9:E73) -> 55 | L4: =SUM(F9:F73) -> 375
A5: B00004 | B5: Silver Z | C5: BODYSPLASH | D5: 12 | E5: =SUMIF(Vm!$C:$C,$A5,Vm!$F:$F) -> 4 | F5: =SUM(D5-E5) -> 8 | G5: OK | I5: 28ml | J5: =SUM(#REF!) -> #REF! | K5: =SUM(E80:E142) -> 296 | L5: =SUM(F80:F142) -> 1057
A6: B00005 | B6: Sunshine | C6: BODYSPLASH | D6: 11 | E6: =SUMIF(Vm!$C:$C,$A6,Vm!$F:$F) -> 4 | F6: =SUM(D6-E6) -> 7 | G6: OK | I6: 50ml | J6: =SUM(#REF!) -> #REF! | K6: =SUM( E149:E150) -> 6 | L6: =SUM( F149:F150) -> 31
I7: 100ml | J7: =SUM(#REF!) -> #REF! | K7: =SUM(E153:E211) -> 56 | L7: =SUM(F153:F211) -> 280
A8: Código | B8: Nome do Perfume | C8: Categoria | D8: Inicio | E8: Vendido | F8: Total | G8: Coluna1 | I8: hidratante | J8: =SUM(#REF!) -> #REF! | K8: =SUM(E217:E241) -> 24 | L8: =SUM(F217:F241) -> 275
A9: P01003 | B9: 2 Love - 10 Ml | C9: 10ML | D9: 5 | E9: =SUMIF(Vm!$C:$C,$A9,Vm!$F:$F) -> 0 | F9: =SUM(D9-E9) -> 5 | G9: ok
A10: P01030 | B10: Ahazzo - 10 Ml | C10: 10ML | D10: 5 | E10: =SUMIF(Vm!$C:$C,$A10,Vm!$F:$F) -> 2 | F10: =SUM(D10-E10) -> 3 | G10: ok
A11: P01031 | B11: Animalz - 10 Ml | C11: 10ML | D11: 8 | E11: =SUMIF(Vm!$C:$C,$A11,Vm!$F:$F) -> 1 | F11: =SUM(D11-E11) -> 7 | G11: ok
A12: P01063 | B12: Aurarose-10Ml | C12: 10ML | D12: 7 | E12: =SUMIF(Vm!$C:$C,$A12,Vm!$F:$F) -> 0 | F12: =SUM(D12-E12) -> 7 | G12: ok
A13: P01001 | B13: Autêntica - 10 Ml | C13: 10ML | D13: 9 | E13: =SUMIF(Vm!$C:$C,$A13,Vm!$F:$F) -> 0 | F13: =SUM(D13-E13) -> 9 | G13: ok
A14: P01004 | B14: Beauty - 10 Ml | C14: 10ML | D14: 4 | E14: =SUMIF(Vm!$C:$C,$A14,Vm!$F:$F) -> 0 | F14: =SUM(D14-E14) -> 4 | G14: ok
A15: P01032 | B15: Black Horse - 10 Ml | C15: 10ML | D15: 6 | E15: =SUMIF(Vm!$C:$C,$A15,Vm!$F:$F) -> 0 | F15: =SUM(D15-E15) -> 6 | G15: ok
A16: P01033 | B16: Blue De Zyone - 10 Ml | C16: 10ML | D16: 7 | E16: =SUMIF(Vm!$C:$C,$A16,Vm!$F:$F) -> 2 | F16: =SUM(D16-E16) -> 5 | G16: ok
A17: P01034 | B17: Boss Man - 10 Ml | C17: 10ML | D17: 7 | E17: =SUMIF(Vm!$C:$C,$A17,Vm!$F:$F) -> 2 | F17: =SUM(D17-E17) -> 5 | G17: ok
A18: P01035 | B18: Bravus - 10 Ml | C18: 10ML | D18: 7 | E18: =SUMIF(Vm!$C:$C,$A18,Vm!$F:$F) -> 0 | F18: =SUM(D18-E18) -> 7 | G18: ok
A19: P01005 | B19: Brz Blossom -10 Ml | C19: 10ML | D19: 7 | E19: =SUMIF(Vm!$C:$C,$A19,Vm!$F:$F) -> 3 | F19: =SUM(D19-E19) -> 4 | G19: ok
A20: P01036 | B20: Brz Dark - 10 Ml | C20: 10ML | D20: 6 | E20: =SUMIF(Vm!$C:$C,$A20,Vm!$F:$F) -> 2 | F20: =SUM(D20-E20) -> 4 | G20: ok
... A77: P01060 | B77: Zayan - 10 Ml | C77: 10ML | D77: 16 | E77: =SUMIF(Vm!$C:$C,$A77,Vm!$F:$F) -> 3 | F77: =SUM(D77-E77) -> 13 | G77: ok
A79: Código | B79: Nome do Perfume | C79: Categoria | D79: Inicio | E79: Vendido | F79: Total | G79: Coluna2 | H79: Coluna3
A80: P02803 | B80: 2 Love - 28 Ml | C80: 28ML | D80: 9 | E80: =SUMIF(Vm!$C:$C,$A80,Vm!$F:$F) -> 0 | F80: =SUM(D80-E80) -> 9 | G80: ok | H80: 46093
A81: P02800 | B81: Aurarose- 28 Ml | C81: 28ML | D81: 47 | E81: =SUMIF(Vm!$C:$C,$A81,Vm!$F:$F) -> 4 | F81: =SUM(D81-E81) -> 43 | G81: ok | J81: 9
A82: P02801 | B82: Autêntica - 28 Ml | C82: 28ML | D82: 9 | E82: =SUMIF(Vm!$C:$C,$A82,Vm!$F:$F) -> 1 | F82: =SUM(D82-E82) -> 8 | G82: ok
A83: P02804 | B83: Beauty - 28 Ml | C83: 28ML | D83: 5 | E83: =SUMIF(Vm!$C:$C,$A83,Vm!$F:$F) -> 0 | F83: =SUM(D83-E83) -> 5 | G83: ok
A84: P02805 | B84: Brz Blossom- 28 Ml | C84: 28ML | D84: 59 | E84: =SUMIF(Vm!$C:$C,$A84,Vm!$F:$F) -> 13 | F84: =SUM(D84-E84) -> 46 | G84: ok
A85: P02806 | B85: Brz Intense Woman- 28 Ml | C85: 28ML | D85: 11 | E85: =SUMIF(Vm!$C:$C,$A85,Vm!$F:$F) -> 1 | F85: =SUM(D85-E85) -> 10 | G85: ok
A86: P02825 | B86: Brz Woman - 28 Ml | C86: 28ML | D86: 15 | E86: =SUMIF(Vm!$C:$C,$A86,Vm!$F:$F) -> 4 | F86: =SUM(D86-E86) -> 11 | G86: ok
A87: P02807 | B87: Cintilante - 28 Ml | C87: 28ML | D87: 7 | E87: =SUMIF(Vm!$C:$C,$A87,Vm!$F:$F) -> 1 | F87: =SUM(D87-E87) -> 6 | G87: ok
A88: P02808 | B88: Creta - 28 Ml | C88: 28ML | D88: 29 | E88: =SUMIF(Vm!$C:$C,$A88,Vm!$F:$F) -> 1 | F88: =SUM(D88-E88) -> 28 | G88: ok
A89: P02857 | B89: Dunes - 28 Ml | C89: 28ML | D89: 7 | E89: =SUMIF(Vm!$C:$C,$A89,Vm!$F:$F) -> 4 | F89: =SUM(D89-E89) -> 3 | G89: ok
A90: P02809 | B90: Five Z - 28 Ml | C90: 28ML | D90: 10 | E90: =SUMIF(Vm!$C:$C,$A90,Vm!$F:$F) -> 0 | F90: =SUM(D90-E90) -> 10 | G90: ok
A91: P02802 | B91: Glow - 28 Ml | C91: 28ML | D91: 34 | E91: =SUMIF(Vm!$C:$C,$A91,Vm!$F:$F) -> 8 | F91: =SUM(D91-E91) -> 26 | G91: ok
A92: P02810 | B92: Gold Woman - 28 Ml | C92: 28ML | D92: 11 | E92: =SUMIF(Vm!$C:$C,$A92,Vm!$F:$F) -> 1 | F92: =SUM(D92-E92) -> 10 | G92: ok
A93: P02811 | B93: Gs - 28 Ml | C93: 28ML | D93: 7 | E93: =SUMIF(Vm!$C:$C,$A93,Vm!$F:$F) -> 0 | F93: =SUM(D93-E93) -> 7 | G93: ok
... A124: P02838 | B124: Brz Intense Men - 28 Ml | C124: 28ML | D124: 9 | E124: =SUMIF(Vm!$C:$C,$A124,Vm!$F:$F) -> 0 | F124: =SUM(D124-E124) -> 9 | G124: ok
A125: P02839 | B125: Brz Men - 28 Ml | C125: 28ML | D125: 29 | E125: =SUMIF(Vm!$C:$C,$A125,Vm!$F:$F) -> 3 | F125: =SUM(D125-E125) -> 26 | G125: -1
A126: P02840 | B126: Brz Urban - 28 Ml | C126: 28ML | D126: 9 | E126: =SUMIF(Vm!$C:$C,$A126,Vm!$F:$F) -> 2 | F126: =SUM(D126-E126) -> 7 | G126: ok
A127: P02841 | B127: Champion - 28 Ml | C127: 28ML | D127: 37 | E127: =SUMIF(Vm!$C:$C,$A127,Vm!$F:$F) -> 2 | F127: =SUM(D127-E127) -> 35 | G127: ok
A128: P02842 | B128: Charmy - 28 Ml | C128: 28ML | D128: 22 | E128: =SUMIF(Vm!$C:$C,$A128,Vm!$F:$F) -> 1 | F128: =SUM(D128-E128) -> 21 | G128: ok
A129: P02843 | B129: Code Man - 28 Ml | C129: 28ML | D129: 22 | E129: =SUMIF(Vm!$C:$C,$A129,Vm!$F:$F) -> 0 | F129: =SUM(D129-E129) -> 22 | G129: ok
A130: P02827 | B130: Conquest - 28 Ml | C130: 28ML | D130: 13 | E130: =SUMIF(Vm!$C:$C,$A130,Vm!$F:$F) -> 4 | F130: =SUM(D130-E130) -> 9 | G130: ok
A131: P02844 | B131: Elegante Sport - 28 Ml | C131: 28ML | D131: 24 | E131: =SUMIF(Vm!$C:$C,$A131,Vm!$F:$F) -> 3 | F131: =SUM(D131-E131) -> 21 | G131: ok
A132: P02845 | B132: Jump! - 28 Ml | C132: 28ML | D132: 6 | E132: =SUMIF(Vm!$C:$C,$A132,Vm!$F:$F) -> 1 | F132: =SUM(D132-E132) -> 5 | G132: ok
A133: P02846 | B133: Lord - 28 Ml | C133: 28ML | D133: 6 | E133: =SUMIF(Vm!$C:$C,$A133,Vm!$F:$F) -> 2 | F133: =SUM(D133-E133) -> 4 | G133: ok
A134: P02847 | B134: Lord Green - 28 Ml | C134: 28ML | D134: 7 | E134: =SUMIF(Vm!$C:$C,$A134,Vm!$F:$F) -> 0 | F134: =SUM(D134-E134) -> 7 | G134: ok
A135: P02848 | B135: Loyal - 28 Ml | C135: 28ML | D135: 7 | E135: =SUMIF(Vm!$C:$C,$A135,Vm!$F:$F) -> 0 | F135: =SUM(D135-E135) -> 7 | G135: ok
A136: P02828 | B136: Noble - 28 Ml | C136: 28ML | D136: 9 | E136: =SUMIF(Vm!$C:$C,$A136,Vm!$F:$F) -> 0 | F136: =SUM(D136-E136) -> 9 | G136: ok
A137: P02829 | B137: Personal Z - 28 Ml | C137: 28ML | D137: 18 | E137: =SUMIF(Vm!$C:$C,$A137,Vm!$F:$F) -> 4 | F137: =SUM(D137-E137) -> 14 | G137: ok
... A146: P02858 | B146: Golden Arabian - 28 Ml | C146: 28ML | D146: 17 | E146: =SUMIF(Vm!$C:$C,$A146,Vm!$F:$F) -> 1 | F146: =SUM(D146-E146) -> 16 | G146: ok
A148: Código | B148: Nome do Perfume | C148: Categoria | D148: Inicio | E148: Vendido | F148: Total | G148: Coluna1 | H148: Coluna2
A149: P05001 | B149: Darion - 50 Ml | C149: 50ML | D149: 22 | E149: =SUMIF(Vm!$C:$C,$A149,Vm!$F:$F) -> 1 | F149: =SUM(D149-E149) -> 21 | G149: 1
A150: P05002 | B150: Yria - 50 Ml | C150: 50ML | D150: 15 | E150: =SUMIF(Vm!$C:$C,$A150,Vm!$F:$F) -> 5 | F150: =SUM(D150-E150) -> 10 | G150: ok
A152: Código | B152: Nome do Perfume | C152: Categoria | D152: Inicio | E152: Vendido | F152: Total | G152: Coluna1 | H152: Coluna2
A153: P10010 | B153: 2 Love - 100 Ml | C153: 100ML | D153: 3 | E153: =SUMIF(Vm!$C:$C,$A153,Vm!$F:$F) -> 0 | F153: =SUM(D153-E153) -> 3 | G153: ok
A154: P10034 | B154: Ahazzo - 100 Ml | C154: 100ML | D154: 3 | E154: =SUMIF(Vm!$C:$C,$A154,Vm!$F:$F) -> 2 | F154: =SUM(D154-E154) -> 1 | G154: ok
A155: P10035 | B155: Animalz - 100 Ml | C155: 100ML | D155: 4 | E155: =SUMIF(Vm!$C:$C,$A155,Vm!$F:$F) -> 1 | F155: =SUM(D155-E155) -> 3 | G155: ok
A156: P10064 | B156: Aura Rose- 100Ml | C156: 100ML | D156: 1 | E156: =SUMIF(Vm!$C:$C,$A156,Vm!$F:$F) -> 0 | F156: =SUM(D156-E156) -> 1 | G156: ok
A157: P10001 | B157: Autêntica - 100 Ml | C157: 100ML | D157: 4 | E157: =SUMIF(Vm!$C:$C,$A157,Vm!$F:$F) -> 0 | F157: =SUM(D157-E157) -> 4 | G157: ok
A158: P10011 | B158: Beauty - 100 Ml | C158: 100ML | D158: 0 | E158: =SUMIF(Vm!$C:$C,$A158,Vm!$F:$F) -> 0 | F158: =SUM(D158-E158) -> 0 | G158: ok
A159: P10036 | B159: Black Horse - 100 Ml | C159: 100ML | D159: 3 | E159: =SUMIF(Vm!$C:$C,$A159,Vm!$F:$F) -> 1 | F159: =SUM(D159-E159) -> 2 | G159: ok
A160: P10037 | B160: Blue De Zyone - 100 Ml | C160: 100ML | D160: 8 | E160: =SUMIF(Vm!$C:$C,$A160,Vm!$F:$F) -> 0 | F160: =SUM(D160-E160) -> 8 | G160: ok
A161: P10038 | B161: Boss Man - 100 ML | C161: 100ML | D161: 9 | E161: =SUMIF(Vm!$C:$C,$A161,Vm!$F:$F) -> 4 | F161: =SUM(D161-E161) -> 5 | G161: ok
A162: P10039 | B162: Bravus - 100 Ml | C162: 100ML | D162: 6 | E162: =SUMIF(Vm!$C:$C,$A162,Vm!$F:$F) -> 0 | F162: =SUM(D162-E162) -> 6 | G162: ok
A163: P10012 | B163: Brz Blossom - 100 Ml | C163: 100ML | D163: 19 | E163: =SUMIF(Vm!$C:$C,$A163,Vm!$F:$F) -> 4 | F163: =SUM(D163-E163) -> 15 | G163: ok
A164: P10040 | B164: Brz Dark - 100 Ml | C164: 100ML | D164: 15 | E164: =SUMIF(Vm!$C:$C,$A164,Vm!$F:$F) -> 0 | F164: 16 | G164: 1
A165: P10041 | B165: Brz Intense Men- 100 Ml | C165: 100ML | D165: 2 | E165: =SUMIF(Vm!$C:$C,$A165,Vm!$F:$F) -> 1 | F165: =SUM(D165-E165) -> 1 | G165: ok
A166: P10002 | B166: Brz Intense Woman - 100 Ml | C166: 100ML | D166: 4 | E166: =SUMIF(Vm!$C:$C,$A166,Vm!$F:$F) -> 0 | F166: =SUM(D166-E166) -> 4 | G166: ok
A167: P10042 | B167: Brz Men -100 Ml | C167: 100ML | D167: 5 | E167: =SUMIF(Vm!$C:$C,$A167,Vm!$F:$F) -> 2 | F167: =SUM(D167-E167) -> 3 | G167: ok
A168: P10043 | B168: Brz Urban - 100 Ml | C168: 100ML | D168: 3 | E168: =SUMIF(Vm!$C:$C,$A168,Vm!$F:$F) -> 0 | F168: =SUM(D168-E168) -> 3 | G168: ok
A169: P10013 | B169: Brz Woman - 100 Ml | C169: 100ML | D169: 5 | E169: =SUMIF(Vm!$C:$C,$A169,Vm!$F:$F) -> 1 | F169: =SUM(D169-E169) -> 4 | G169: ok
A170: P10044 | B170: Champion - 100 Ml | C170: 100ML | D170: 14 | E170: =SUMIF(Vm!$C:$C,$A170,Vm!$F:$F) -> 2 | F170: =SUM(D170-E170) -> 12 | G170: ok
A171: P10045 | B171: Charmy - 100 Ml | C171: 100ML | D171: 9 | E171: =SUMIF(Vm!$C:$C,$A171,Vm!$F:$F) -> 0 | F171: =SUM(D171-E171) -> 9 | G171: ok
A172: P10014 | B172: Cintilante - 100 Ml | C172: 100ML | D172: 0 | E172: =SUMIF(Vm!$C:$C,$A172,Vm!$F:$F) -> 0 | F172: =SUM(D172-E172) -> 0 | G172: ok
A173: P10046 | B173: Code Man - 100 M | C173: 100ML | D173: 7 | E173: =SUMIF(Vm!$C:$C,$A173,Vm!$F:$F) -> 1 | F173: =SUM(D173-E173) -> 6 | G173: ok
A174: P10026 | B174: Conquest - 100 Ml | C174: 100ML | D174: 4 | E174: =SUMIF(Vm!$C:$C,$A174,Vm!$F:$F) -> 1 | F174: =SUM(D174-E174) -> 3 | G174: ok
A175: P10015 | B175: Creta - 100 Ml | C175: 100ML | D175: 5 | E175: =SUMIF(Vm!$C:$C,$A175,Vm!$F:$F) -> 2 | F175: =SUM(D175-E175) -> 3 | G175: ok
A176: P10056 | B176: Dunes - 100 Ml | C176: 100ML | D176: 2 | E176: =SUMIF(Vm!$C:$C,$A176,Vm!$F:$F) -> 0 | F176: =SUM(D176-E176) -> 2 | G176: ok
... A188: P10047 | B188: Lord Green - 100 Ml | C188: 100ML | D188: 5 | E188: =SUMIF(Vm!$C:$C,$A188,Vm!$F:$F) -> 1 | F188: =SUM(D188-E188) -> 4 | G188: ok
A189: P10019 | B189: Love It - 100 Ml | C189: 100ML | D189: 6 | E189: =SUMIF(Vm!$C:$C,$A189,Vm!$F:$F) -> 2 | F189: =SUM(D189-E189) -> 4 | G189: 2
A190: P10048 | B190: Loyal - 100 Ml | C190: 100ML | D190: 1 | E190: =SUMIF(Vm!$C:$C,$A190,Vm!$F:$F) -> 1 | F190: =SUM(D190-E190) -> 0 | G190: ok
A191: P10005 | B191: Luminous Flowers - 100 Ml | C191: 100ML | D191: 7 | E191: =SUMIF(Vm!$C:$C,$A191,Vm!$F:$F) -> 1 | F191: =SUM(D191-E191) -> 6 | G191: ok
A192: P10020 | B192: Luminous Girl - 100 Ml | C192: 100ML | D192: 17 | E192: =SUMIF(Vm!$C:$C,$A192,Vm!$F:$F) -> 3 | F192: =SUM(D192-E192) -> 14 | G192: ok
A193: P10021 | B193: Lys - 100 Ml | C193: 100ML | D193: 5 | E193: =SUMIF(Vm!$C:$C,$A193,Vm!$F:$F) -> 0 | F193: =SUM(D193-E193) -> 5 | G193: ok
A194: P10022 | B194: Magic - 100 Ml | C194: 100ML | D194: 2 | E194: =SUMIF(Vm!$C:$C,$A194,Vm!$F:$F) -> 0 | F194: =SUM(D194-E194) -> 2 | G194: ok
A195: P10053 | B195: Malirah - 100 Ml | C195: 100ML | D195: 14 | E195: =SUMIF(Vm!$C:$C,$A195,Vm!$F:$F) -> 0 | F195: =SUM(D195-E195) -> 14 | G195: ok
A196: P10023 | B196: Miss - 100 Ml | C196: 100ML | D196: 8 | E196: =SUMIF(Vm!$C:$C,$A196,Vm!$F:$F) -> 1 | F196: =SUM(D196-E196) -> 7 | G196: ok
A197: P10054 | B197: Naiad - 100 Ml | C197: 100ML | D197: 9 | E197: =SUMIF(Vm!$C:$C,$A197,Vm!$F:$F) -> 0 | F197: =SUM(D197-E197) -> 9 | G197: ok
A198: P10030 | B198: Noble - 100 Ml | C198: 100ML | D198: 1 | E198: =SUMIF(Vm!$C:$C,$A198,Vm!$F:$F) -> 0 | F198: =SUM(D198-E198) -> 1 | G198: ok
A199: P10031 | B199: Personal Z - 100 Ml | C199: 100ML | D199: 1 | E199: =SUMIF(Vm!$C:$C,$A199,Vm!$F:$F) -> 0 | F199: =SUM(D199-E199) -> 1 | G199: ok
A200: P10024 | B200: Revolution - 100 Ml | C200: 100ML | D200: 13 | E200: =SUMIF(Vm!$C:$C,$A200,Vm!$F:$F) -> 3 | F200: =SUM(D200-E200) -> 10 | G200: ok
A201: P10058 | B201: Rubi - 100 Ml | C201: 100ML | D201: 17 | E201: =SUMIF(Vm!$C:$C,$A201,Vm!$F:$F) -> 2 | F201: =SUM(D201-E201) -> 15 | G201: ok
... A214: P10060 | B214: Zayan - 100 Ml | C214: 100ML | D214: 15 | E214: =SUMIF(Vm!$C:$C,$A214,Vm!$F:$F) -> 0 | F214: =SUM(D214-E214) -> 15 | G214: ok
F215: =SUM(D215-E215) -> 0
A216: Código | B216: Nome do Perfume | C216: Categoria | D216: Inicio | E216: Vendido | F216: Total
A217: H00014 | B217: 121 Men Brz - Hidratante | C217: Hidratante | D217: 24 | E217: =SUMIF(Vm!$C:$C,$A217,Vm!$F:$F) -> 0 | F217: =SUM(D217-E217) -> 24
A218: H00001 | B218: 121 Sexy - Hidratante | C218: Hidratante | D218: 8 | E218: =SUMIF(Vm!$C:$C,$A218,Vm!$F:$F) -> 0 | F218: =SUM(D218-E218) -> 8
A219: H00015 | B219: 121 Vip Black - Hidratante | C219: Hidratante | D219: 15 | E219: =SUMIF(Vm!$C:$C,$A219,Vm!$F:$F) -> 3 | F219: =SUM(D219-E219) -> 12
A220: H00002 | B220: Blossom - Hidratante | C220: Hidratante | D220: 20 | E220: =SUMIF(Vm!$C:$C,$A220,Vm!$F:$F) -> 1 | F220: =SUM(D220-E220) -> 19
...

Sheet Vm
A1: Mês/Ano | B1: Nome | C1: Código | D1: Nome do Perfume | E1: Produto | F1: Quantidade Vendida | G1: Valor de custo/ empresa | H1: Valor Unitário | I1: Valor Total da Venda | J1: Situação
A2: 46082 | B2: Junin ( Paulo Cesar) | C2: P02819 | D2: Miss - Perfume 28 Ml | E2: 28ML | F2: 1
A3: 46082 | B3: Matheus Rici | C3: P02851 | D3: Silver Z - 28 Ml | E3: 28ML | F3: 1 | J3: Pago
A4: 46082 | B4: Junin ( Paulo Cesar) | C4: B00005 | D4: Sunshine | E4: BODYSPLASH | F4: 1 | J4: Pago
A5: 46083 | B5: Alberto Henrique | C5: P10005 | D5: Luminous Flowers - Perfume 100 Ml | E5: 100ML | F5: 1 | J5: Pago
A6: 46083 | B6: Alberto Henrique | C6: P10013 | D6: Brz Woman (121 Woman Brz) - Perfume 100 Ml | E6: 100ML | F6: 1 | J6: Pago
A7: 46083 | B7: Alberto Henrique | C7: P10038 | D7: Boss Man - Perfume 100 ML | E7: 100ML | F7: 1 | J7: Pago
A8: 46083 | B8: Neiz Vidal | C8: P01005 | D8: Brz Blossom -10 Ml | E8: 10ML | F8: 1
A9: 46083 | B9: Neiz Vidal | C9: P01053 | D9: Malirah - 10 Ml | E9: 10ML | F9: 1
A10: 46083 | B10: Neiz Vidal | C10: P01030 | D10: Ahazzo - 10 Ml | E10: 10ML | F10: 1
A11: 46083 | B11: Neiz Vidal | C11: P01034 | D11: Boss Man - 10 Ml | E11: 10ML | F11: 1
A12: 46083 | B12: Neiz Vidal | C12: P01033 | D12: Blue De Zyone - 10 Ml | E12: 10ML | F12: 1
A13: 46083 | B13: Neiz Vidal | C13: P01036 | D13: Brz Dark - 10 Ml | E13: 10ML | F13: 1
A14: 46083 | B14: Neiz Vidal | C14: P01039 | D14: Champion - 10 Ml | E14: 10ML | F14: 1
A15: 46083 | B15: Neiz Vidal | C15: P01040 | D15: Charmy - 10 Ml | E15: 10ML | F15: 1
A16: 46083 | B16: Neiz Vidal | C16: P01049 | D16: Selvagem - 10 Ml | E16: 10ML | F16: 1
A17: 46083 | B17: Neiz Vidal | C17: P01050 | D17: Silver Z - 10 Ml | E17: 10ML | F17: 1
A18: 46083 | B18: Neiz Vidal | C18: P01055 | D18: Sharif - 10 Ml | E18: 10ML | F18: 1
A19: 46083 | B19: Neiz Vidal | C19: P01060 | D19: Zayan - 10 Ml | E19: 10ML | F19: 1
... A27: 46083 | B27: Neiz Vidal | C27: P01058 | D27: Rubi - 10 Ml | E27: 10ML | F27: 1
A28: 46083 | B28: Alberto Henrique | C28: P02851 | D28: Silver Z - Perfume 28 Ml | E28: 28ML | F28: 1 | J28: Pago
A29: 46083 | B29: Junin ( Paulo Cesar) | C29: P02815 | D29: Luminous Flowers - 28 Ml | E29: 28ML | F29: 1
A30: 46083 | B30: Leo Souza | C30: P02822 | D30: Sweet Blue - 28 Ml | E30: 28ML | F30: 1 | J30: Pago
A31: 46083 | B31: Leo Souza | C31: P02824 | D31: Tuberose Shine - 28 Ml | E31: 28ML | F31: 1 | J31: Pago
A32: 46083 | B32: Yuri Origem | C32: P02816 | D32: Luminous Girl (Nice Girl) - Perfume 28 Ml | E32: 28ML | F32: 1 | J32: Pago
A33: 46083 | B33: Yuri Origem | C33: P02850 | D33: Selvagem - Perfume 28 Ml | E33: 28ML | F33: 1 | J33: Pago
A34: 46084 | B34: Junin ( Paulo Cesar) | C34: P10012 | D34: Brz Blossom - 100 Ml | E34: 100ML | F34: 1 | J34: Pago
A35: 46084 | B35: Luciano | C35: P10046 | D35: Code Man - 100 M | E35: 100ML | F35: 1
A36: 46084 | B36: Luciano | C36: P10036 | D36: Black Horse - 100 Ml | E36: 100ML | F36: 1
A37: 46084 | B37: Luciano | C37: P10020 | D37: Luminous Girl - 100 Ml | E37: 100ML | F37: 1
A38: 46084 | B38: Luciano | C38: P10015 | D38: Creta - 100 Ml | E38: 100ML | F38: 1
A39: 46084 | B39: Luciano | C39: P10050 | D39: Selvagem - 100 Ml | E39: 100ML | F39: 2
A40: 46084 | B40: Matheus Rici | C40: P10034 | D40: Ahazzo - 100 Ml | E40: 100ML | F40: 1 | J40: Pago
A41: 46084 | B41: Pedrão | C41: P10038 | D41: Boss Man - 100 ML | E41: 100ML | F41: 1 | J41: Pago
A42: 46084 | B42: Thiago Cotuba | C42: P10018 | D42: La Vie Est Amour - 100 Ml | E42: 100ML | F42: 1 | J42: Pago
A43: 46084 | B43: Junin ( Paulo Cesar) | C43: P02829 | D43: Personal Z - 28 Ml | E43: 28ML | F43: 1
A44: 46084 | B44: Luciano | C44: P02825 | D44: Brz Woman - 28 Ml | E44: 28ML | F44: 1
A45: 46084 | B45: Luciano | C45: P02850 | D45: Selvagem - 28 Ml | E45: 28ML | F45: 1
A46: 46084 | B46: Mayra | C46: P02802 | D46: Glow - 28 Ml | E46: 28ML | F46: 1
A47: 46084 | B47: Tauan | C47: P02815 | D47: Luminous Flowers - 28 Ml | E47: 28ML | F47: 2 | J47: Pago
A48: 46084 | B48: Pedrão | C48: B00002 | D48: Nectar Crystal | E48: BODYSPLASH | F48: 1
A49: 46084 | B49: Pedrão | C49: B00004 | D49: Silver Z | E49: BODYSPLASH | F49: 1
A50: 46084 | B50: Pedrão | C50: H00015 | D50: 121 Vip Black - Hidratante | E50: Hidratante | F50: 1
A51: 46084 | B51: Pedrão | C51: H00021 | D51: Silver Z - Hidratante | E51: Hidratante | F51: 1
A52: 46085 | B52: Vitoria Cardoso | C52: P10050 | D52: Selvagem - 100 Ml | E52: 100ML | F52: 1 | J52: Pago
A53: 46085 | B53: Vitoria Cardoso | C53: P10058 | D53: Rubi - 100 Ml | E53: 100ML | F53: 1 | J53: Pago
A54: 46085 | B54: Vitoria Cardoso | C54: P10003 | D54: Glow - 100 Ml | E54: 100ML | F54: 1 | J54: Pago
A55: 46085 | B55: Eduardo | C55: P01066 | D55: Yria-10Ml | E55: 10ML | F55: 3 | J55: Pago
A56: 46085 | B56: Eduardo | C56: P01068 | D56: Outono- 10ML | E56: 10ML | F56: 2 | J56: Pago
A57: 46085 | B57: Eduardo | C57: P01017 | D57: Luminous Flowers - 10 Ml | E57: 10ML | F57: 2 | J57: Pago
A58: 46085 | B58: Vitoria Cardoso | C58: P01066 | D58: Yria-10Ml | E58: 10ML | F58: 1 | J58: Pago
A59: 46085 | B59: Eduardo | C59: P02827 | D59: Conquest - 28 Ml | E59: 28ML | F59: 2 | J59: Pago
A60: 46085 | B60: Eduardo | C60: P02858 | D60: Golden Arabian - 28 Ml | E60: 28ML | F60: 1 | J60: Pago
A61: 46085 | B61: Eduardo | C61: P02813 | D61: La Vie Est Amour - 28 Ml | E61: 28ML | F61: 2 | J61: Pago
A62: 46085 | B62: Eduardo | C62: P02816 | D62: Luminous Girl - 28 Ml | E62: 28ML | F62: 2 | J62: Pago
A63: 46085 | B63: Eduardo | C63: P02866 | D63: Outono- 28Ml | E63: 28ML | F63: 6 | J63: Pago
... A78: 46086 | B78: Afonso Siqueira | C78: P10050 | D78: Selvagem - 100 Ml | E78: 100ML | F78: 1 | J78: Pago
A79: 46086 | B79: Felipe Santos | C79: P10051 | D79: Silver Z - 100 Ml | E79: 100ML | F79: 1
A80: 46086 | B80: Lucas Pedroso | C80: P10012 | D80: Brz Blossom - 100 Ml | E80: 100ML | F80: 1 | J80: Pago
A81: 46086 | B81: Lucas Pedroso | C81: P10050 | D81: Selvagem - 100 Ml | E81: 100ML | F81: 1 | J81: Pago
A82: 46086 | B82: Maninho | C82: P10020 | D82: Luminous Girl - 100 Ml | E82: 100ML | F82: 1 | J82: Pago
A83: 46086 | B83: Pedrão | C83: P10050 | D83: Selvagem - 100 Ml | E83: 100ML | F83: 1 | J83: Pago
A84: 46086 | B84: Afonso Siqueira | C84: P01005 | D84: Brz Blossom -10 Ml | E84: 10ML | F84: 1 | J84: Pago
A85: 46086 | B85: Afonso Siqueira | C85: P01060 | D85: Zayan - 10 Ml | E85: 10ML | F85: 1 | J85: Pago
A86: 46086 | B86: Ana ( Felipe Araujo) | C86: P01058 | D86: Rubi - 10 Ml | E86: 10ML | F86: 1 | J86: Pago
A87: 46086 | B87: Lucas Pedroso | C87: P01053 | D87: Malirah - 10 Ml | E87: 10ML | F87: 1 | J87: Pago
A88: 46086 | B88: Lucas Pedroso | C88: P01059 | D88: Sunshine - 10 Ml | E88: 10ML | F88: 1 | J88: Pago
A89: 46086 | B89: Maninho | C89: P01050 | D89: Silver Z - 10 Ml | E89: 10ML | F89: 1 | J89: Pago
A90: 46086 | B90: Maycon Rampin | C90: P01049 | D90: Selvagem - 10 Ml | E90: 10ML | F90: 1 | J90: Pago
A91: 46086 | B91: Yuri Origem | C91: P01031 | D91: Animalz - 10 Ml | E91: 10ML | F91: 1 | J91: Pago
... A95: 46086 | B95: Dalton Zili | C95: P02861 | D95: Zayan - 28 Ml | E95: 28ML | F95: 1 | J95: Pago
A96: 46086 | B96: Felipe Araujo | C96: P02859 | D96: Rubi - 28 Ml | E96: 28ML | F96: 1
A97: 46086 | B97: Felipe Santos | C97: P02832 | D97: Animalz - 28 Ml | E97: 28ML | F97: 1
A98: 46086 | B98: Felipe Santos | C98: P02820 | D98: Revolution - 28 Ml | E98: 28ML | F98: 1
A99: 46086 | B99: Felipe Santos | C99: P02859 | D99: Rubi - 28 Ml | E99: 28ML | F99: 1
A100: 46086 | B100: Felipe Santos | C100: P02850 | D100: Selvagem - 28 Ml | E100: 28ML | F100: 1
A101: 46086 | B101: Lucas Pedroso | C101: P02805 | D101: Brz Blossom- 28 Ml | E101: 28ML | F101: 1 | J101: Pago
A102: 46086 | B102: Lucas Pedroso | C102: P02832 | D102: Animalz - 28 Ml | E102: 28ML | F102: 1 | J102: Pago
A103: 46086 | B103: Lucas Pedroso | C103: P02827 | D103: Conquest - 28 Ml | E103: 28ML | F103: 1 | J103: Pago
A104: 46086 | B104: Lucas Pedroso | C104: P02844 | D104: Elegante Sport - 28 Ml | E104: 28ML | F104: 1 | J104: Pago
A105: 46086 | B105: Lucas Pedroso | C105: P02816 | D105: Luminous Girl - 28 Ml | E105: 28ML | F105: 1 | J105: Pago
A106: 46086 | B106: Lucas Pedroso | C106: P02861 | D106: Zayan - 28 Ml | E106: 28ML | F106: 1 | J106: Pago
A107: 46086 | B107: Lucas Pedroso | C107: P02854 | D107: Malirah - 28 Ml | E107: 28ML | F107: 1 | J107: Pago
A108: 46086 | B108: Maninho | C108: P02859 | D108: Rubi - 28 Ml | E108: 28ML | F108: 2 | J108: Pago
A109: 46086 | B109: Maninho | C109: P02851 | D109: Silver Z - 28 Ml | E109: 28ML | F109: 2 | J109: Pago
A110: 46086 | B110: Maninho | C110: P02854 | D110: Malirah - 28 Ml | E110: 28ML | F110: 2 | J110: Pago
A111: 46086 | B111: Maycon Rampin | C111: P02834 | D111: Blue De Zyone - 28 Ml | E111: 28ML | F111: 1 | J111: Pago
A112: 46086 | B112: Maycon Rampin | C112: P02814 | D112: Love It - 28 Ml | E112: 28ML | F112: 1 | J112: Pago
A113: 46086 | B113: Yuri Origem | C113: P02850 | D113: Selvagem - 28 Ml | E113: 28ML | F113: 1 | J113: Pago
A114: 46086 | B114: Pedrão | C114: B00003 | D114: Rubi | E114: BODYSPLASH | F114: 1
A115: 46086 | B115: Afonso Siqueira | C115: H00010 | D115: Nice Girl - Hidratante | E115: Hidratante | F115: 1 | J115: Pago
A116: 46086 | B116: Ana ( Felipe Araujo) | C116: H00010 | D116: Nice Girl - Hidratante | E116: Hidratante | F116: 1 | J116: Pago
A117: 46086 | B117: Maninho | C117: H00021 | D117: Silver Z - Hidratante | E117: Hidratante | F117: 2 | J117: Pago
A118: 46087 | B118: Eduardo | C118: P10012 | D118: Brz Blossom - 100 Ml | E118: 100ML | F118: 1 | J118: Pago
A119: 46087 | B119: Mayra | C119: P10038 | D119: Boss Man - 100 ML | E119: 100ML | F119: 1 | J119: Pago
A120: 46087 | B120: Vinicius Rezende | C120: P10042 | D120: Brz Men -100 Ml | E120: 100ML | F120: 1 | J120: Pago
A121: 46087 | B121: Vinicius Rezende | C121: P10059 | D121: Sunshine - 100 Ml | E121: 100ML | F121: 1 | J121: Pago
A122: 46087 | B122: Rogerio Pinto ( Eduardo ) | C122: P01049 | D122: Selvagem - 10 Ml | E122: 10ML | F122: 1 | J122: Pago
A123: 46087 | B123: Rogerio Pinto ( Eduardo ) | C123: P01067 | D123: Inverno- 10ML | E123: 10ML | F123: 1 | J123: Pago
A124: 46087 | B124: Rogerio Pinto ( Eduardo ) | C124: P01055 | D124: Sharif - 10 Ml | E124: 10ML | F124: 1 | J124: Pago
...

Sheet Resumo 
A1: Total pago | B1: Total devendo
A2: =SUM(J4:J1002)*-1 -> 0 | B2: =SUM(C5:C97) -> 0
A4: Mês/Ano | B4: Vendedor | C4: Total Vendido (R$) | D4: 10ML | E4: 28ML | F4: 50ML | G4: 100ML | H4: Hidratante | I4: Bodysplash | J4: Total | K4: Pagamento | L4: OBSERVAÇÃO
A5: fev | B5: Eduardo-jan ( 5.000,00)
A6: fev | B6: Felipe Araujo- jan/dez
A7: fev | B7: Felipe Santos-fev
A8: fev | B8: Igor Paes- fev
A9: fev | B9: Isabela Leal- jan
A10: fev | B10: Junin (Paulo Cesar)- fev
A11: fev | B11: Junin (Paulo Cesar)-jan
A12: fev | B12: Leonardo celico-fev
A13: fev | B13: Luciano-fev
A14: fev | B14: Thamiris Bambini-fev
A15: 46091 | B15: Luis Fernando ( energia solar)
A16: 46090 | B16: Isabela Leal
A17: 46088 | B17: Flavio ( queijin)
A18: 46087 | B18: Igor Paes
A19: 46086 | B19: Felipe Santos
A20: 46084 | B20: Luciano
A21: 46084 | B21: Neiz Vidal
A22: 46084 | B22: Pedrão
A23: 46083 | B23: Yuri Origem
A24: 46082 | B24: Junin ( Paulo Cesar)
A25: 46054 | B25: Jonatha sandoval- fev
A26: 46093 | B26: Jonathan Sandoval
... A28: 46084 | B28: Tauan
A29: fev | B29: Eidy-fev
A30: fev | B30: Felipe Araujo-fev
A31: fev | B31: Flavio ( queijin)- jan
A32: fev | B32: Isa Mulher do Thiago- fev
A33: fev | B33: João Previato -fev
A34: fev | B34: Pedrão-fev
A35: 414978 | B35: Alberto Henrique
A36: 46092 | B36: Isa do Thiago
A37: 46092 | B37: Paulo Gouveia
A38: 46091 | B38: Livia Barbosa
A39: 46090 | B39: Alex Rocket League
A40: 46090 | B40: Pedro V.l
A41: 46089 | B41: Arthur Pini
A42: 46089 | B42: Thais Rodrigues
A43: 46088 | B43: Adão Pereira
A44: 46088 | B44: Diego Thomazo
A45: 46088 | B45: Thiago Cotuba
A46: 46087 | B46: Rogerio Pinto ( Eduardo )
... A62: 46097 | B62: Ademar

Sheet Fin
A1: GANHOU ESSE MÊS + DIVIDAS PAGAS | F1: Matheus Rici Lucro | G1: Custo | H1: Total
A2: Ganho Total | F2: =SUM('M Rici vend '!J2:J1000) -> 0 | G2: =SUM('M Rici vend '!H2:H1000) -> 0 | H2: =SUM(F2-G2) -> 0
A3: =SUM('Resumo '!A2) -> 0
A5: GANHO MENSAL + DIVIDA
A6: =SUM('Resumo '!A2:B2) -> 0
A8: DIVIDA devendo
A9: =SUM('Resumo '!B2) -> 0
A11: Ganho mensal
A14: Ganho sem vp
A15: =SUM(A12-F2) -> 0

Sheet M Rici vend 
A1: Data | B1: Cliente | C1: Nascimento | D1: Telefone | E1: Nome | G1: Quantidade | H1: Custo | I1: Valor | J1: lucro | K1: Valor Total
